gtls/__init__.py
gtls/gtls.py
gtls-0.0.2.dist-info/LICENSE
gtls-0.0.2.dist-info/METADATA
gtls-0.0.2.dist-info/WHEEL
gtls-0.0.2.dist-info/top_level.txt
gtls-0.0.2.dist-info/RECORD
