Metadata-Version: 2.1
Name: gtls
Version: 0.0.2
Summary: Some simple tools commonly used in work.
Home-page: https://github.com/FutureNear/Gtls.git
Author: FutureNear
Author-email: futurenear@163.com
License: UNKNOWN
Platform: UNKNOWN
Classifier: Programming Language :: Python :: 3
Classifier: License :: OSI Approved :: MIT License
Classifier: Operating System :: OS Independent
Requires-Python: >=3.6
License-File: LICENSE
